piininja/__init__.py
piininja/core.py
piininja/techniques.py
piininja/utils.py
piininja-0.1.0.dist-info/METADATA
piininja-0.1.0.dist-info/WHEEL
piininja-0.1.0.dist-info/top_level.txt
piininja-0.1.0.dist-info/RECORD
